MANIFEST.in
README.rst
setup.py
clever_selects/__init__.py
clever_selects/admin.py
clever_selects/form_fields.py
clever_selects/forms.py
clever_selects/views.py
clever_selects/widgets.py
clever_selects/static/.DS_Store
clever_selects/static/js/clever-selects.js
clever_selects/templates/clever_selects/widgets/chained_select.html
clever_selects/templatetags/__init__.py
clever_selects/templatetags/clever_selects_extras.py
django_clever_selects_xadmin.egg-info/PKG-INFO
django_clever_selects_xadmin.egg-info/SOURCES.txt
django_clever_selects_xadmin.egg-info/dependency_links.txt
django_clever_selects_xadmin.egg-info/requires.txt
django_clever_selects_xadmin.egg-info/top_level.txt