Metadata-Version: 1.2
Name: django-clever-selects-xadmin
Version: 0.8.8.3
Summary: Chained select box widget for Django framework using AJAX requests.
Home-page: https://github.com/CROXLINK/django-clever-selects
Author: Pragmatic Mates
Author-email: info@pragmaticmates.com
Maintainer: Croxlink
Maintainer-email: eddiep@croxlink.com
License: BSD License
Keywords: django clever chained selects
Platform: UNKNOWN
Classifier: Programming Language :: Python
Classifier: Programming Language :: Python :: 2.5
Classifier: Programming Language :: Python :: 2.6
Classifier: Programming Language :: Python :: 2.7
Classifier: Programming Language :: Python :: 3.4
Classifier: Programming Language :: Python :: 3.5
Classifier: Programming Language :: Python :: 3.6
Classifier: Operating System :: OS Independent
Classifier: Environment :: Web Environment
Classifier: Intended Audience :: Developers
Classifier: Framework :: Django
Classifier: License :: OSI Approved :: BSD License
Classifier: Development Status :: 3 - Alpha
